<?xml version="1.0" encoding="UTF-8"?>
<!DOCTYPE mets:mets [
  <!ENTITY AElig  '&#xC6;'>
  <!ENTITY Eacute '&#xC9;'>
  <!ENTITY eacute '&#xE9;'>
  <!ENTITY egrave '&#xE8;'>
  <!ENTITY ccedil '&#xE7;'>
  <!ENTITY ecirc  '&#xEA;'>
  <!ENTITY aelig  '&#xE6;'>
  <!ENTITY copy   '&#169;'>
  <!ENTITY deg    '&#176;'>
  <!ENTITY nbsp   '&#160;'>
  <!ENTITY ouml   '&#246;'>
]>
<mets:mets xmlns:xsi="http://www.w3.org/2001/XMLSchema-instance"
  xmlns:xlink="http://www.w3.org/1999/xlink"
  xmlns:mets="http://www.loc.gov/METS/"
  xsi:schemaLocation="http://www.loc.gov/METS/ http://www.loc.gov/mets/mets.xsd">
<!-- See e.g. <http://dfg-viewer.de/show/?tx_dlf%5Bid%5D=https%3A%2F%2Fwww.thomasgray.org%2Fimages%2Fdiglib%2Fmets%2F1777.xml&no_cache=1> -->

  <mets:dmdSec ID="diglib-1777-dmd-0000">
    <mets:mdWrap MIMETYPE="text/xml" MDTYPE="MODS">
      <mets:xmlData>
        <mods:mods xmlns:mods="http://www.loc.gov/mods/v3" version="3.3"
          xsi:schemaLocation="http://www.loc.gov/mods/v3 http://www.loc.gov/standards/mods/v3/mods-3-3.xsd">
          <mods:identifier type="urn">urn:x-thomasgrayarchive:grayt.1777</mods:identifier>
          <mods:titleInfo>
            <mods:title> A Letter to W. Mason, A.M. precentor of York, concerning his edition of Mr. Gray's Poems. And the Practices of Booksellers. 
            </mods:title>
          </mods:titleInfo>
          <mods:typeOfResource>still image</mods:typeOfResource>
          <mods:name type="personal" authority="lcnaf">
            <mods:displayForm>Murray, John, 1737-1793</mods:displayForm>
            <mods:role>
              <mods:roleTerm type="text">author</mods:roleTerm>
              <mods:roleTerm authority="marcrelator" type="code">aut</mods:roleTerm>
            </mods:role>
          </mods:name>
          <mods:originInfo>
            <mods:publisher>
               London: printed for J. Murray, (No. 32) Fleet-Street. M DCC LXXVII. 
            </mods:publisher>                        
            <mods:dateCaptured>
              24/08/2007
            </mods:dateCaptured>
            <mods:dateIssued encoding="iso8601" keyDate="yes">1777</mods:dateIssued>
          </mods:originInfo>
          <mods:physicalDescription>
            <mods:extent>
               64p.; 8&deg;.
            </mods:extent>
            <mods:note type="physical description">
              With a half-title. 
            </mods:note>
            <mods:digitalOrigin>reformatted digital</mods:digitalOrigin>
          </mods:physicalDescription>
          <mods:location>
            <mods:physicalLocation>
              Bodleian Library, University of Oxford
            </mods:physicalLocation>              
            <mods:shelfLocator>
               270 g.418 
            </mods:shelfLocator>
          </mods:location>
          <mods:relatedItem type="isReferencedBy">
            <mods:note type="citation/reference">
              Northup 1561
            </mods:note>
          </mods:relatedItem>
          <mods:relatedItem type="isReferencedBy">
            <mods:note type="citation/reference">
              ESTC T4056.
            </mods:note>
          </mods:relatedItem>
          <mods:accessCondition>
            Copyright &copy; 2005 Bodleian Library, University of Oxford; access to digitized documents is granted strictly for non-commercial educational,  research and private purposes only. 
          </mods:accessCondition>
          <mods:recordInfo>
            <mods:recordIdentifier source="TGA">1777</mods:recordIdentifier>
          </mods:recordInfo>
        </mods:mods>
      </mets:xmlData>
    </mets:mdWrap>
  </mets:dmdSec>

  <mets:amdSec ID="diglib-1777-amd-0000">
    <mets:rightsMD ID="diglib1777-amd-rights-0000">
      <mets:mdWrap MIMETYPE="text/xml" MDTYPE="OTHER" OTHERMDTYPE="DVRIGHTS">
        <mets:xmlData>
          <dv:rights xmlns:dv="http://dfg-viewer.de/">
            <dv:owner>Thomas Gray Archive</dv:owner>
            <dv:ownerContact>mailto:info@thomasgray.org</dv:ownerContact>
            <dv:ownerLogo>https://www.thomasgray.org/images/logo_collage4.png</dv:ownerLogo>
            <dv:ownerSiteURL>https://www.thomasgray.org/</dv:ownerSiteURL>
          </dv:rights>
        </mets:xmlData>
      </mets:mdWrap>
    </mets:rightsMD>
    <mets:digiprovMD ID="diglib-1777-amd-digiprov-0000">
      <mets:mdWrap MIMETYPE="text/xml" MDTYPE="OTHER" OTHERMDTYPE="DVLINKS">
        <mets:xmlData>
          <dv:links xmlns:dv="http://dfg-viewer.de/">
            <dv:reference>https://www.thomasgray.org/cgi-bin/view.cgi?collection=secondary&amp;edition=1777#record</dv:reference>
            <dv:presentation>https://www.thomasgray.org/cgi-bin/view.cgi?collection=secondary&amp;edition=1777</dv:presentation>
          </dv:links>
        </mets:xmlData>
      </mets:mdWrap>
    </mets:digiprovMD>
  </mets:amdSec>

  <mets:fileSec>
    <mets:fileGrp USE="DEFAULT">
      <mets:file MIMETYPE="image/gif" ID="diglib-1777-img-0001_100">
        <mets:FLocat LOCTYPE="URL" xlink:href="https://www.thomasgray.org/images/diglib/secondary/1777/0001.gif"/>
      </mets:file>
      <mets:file MIMETYPE="image/gif" ID="diglib-1777-img-0002_100">
        <mets:FLocat LOCTYPE="URL" xlink:href="https://www.thomasgray.org/images/diglib/secondary/1777/0002.gif"/>
      </mets:file>
      <mets:file MIMETYPE="image/gif" ID="diglib-1777-img-0003_100">
        <mets:FLocat LOCTYPE="URL" xlink:href="https://www.thomasgray.org/images/diglib/secondary/1777/0003.gif"/>
      </mets:file>
      <mets:file MIMETYPE="image/gif" ID="diglib-1777-img-0004_100">
        <mets:FLocat LOCTYPE="URL" xlink:href="https://www.thomasgray.org/images/diglib/secondary/1777/0004.gif"/>
      </mets:file>
      <mets:file MIMETYPE="image/gif" ID="diglib-1777-img-0005_100">
        <mets:FLocat LOCTYPE="URL" xlink:href="https://www.thomasgray.org/images/diglib/secondary/1777/0005.gif"/>
      </mets:file>
      <mets:file MIMETYPE="image/gif" ID="diglib-1777-img-0006_100">
        <mets:FLocat LOCTYPE="URL" xlink:href="https://www.thomasgray.org/images/diglib/secondary/1777/0006.gif"/>
      </mets:file>
      <mets:file MIMETYPE="image/gif" ID="diglib-1777-img-0007_100">
        <mets:FLocat LOCTYPE="URL" xlink:href="https://www.thomasgray.org/images/diglib/secondary/1777/0007.gif"/>
      </mets:file>
      <mets:file MIMETYPE="image/gif" ID="diglib-1777-img-0008_100">
        <mets:FLocat LOCTYPE="URL" xlink:href="https://www.thomasgray.org/images/diglib/secondary/1777/0008.gif"/>
      </mets:file>
      <mets:file MIMETYPE="image/gif" ID="diglib-1777-img-0009_100">
        <mets:FLocat LOCTYPE="URL" xlink:href="https://www.thomasgray.org/images/diglib/secondary/1777/0009.gif"/>
      </mets:file>
      <mets:file MIMETYPE="image/gif" ID="diglib-1777-img-0010_100">
        <mets:FLocat LOCTYPE="URL" xlink:href="https://www.thomasgray.org/images/diglib/secondary/1777/0010.gif"/>
      </mets:file>
      <mets:file MIMETYPE="image/gif" ID="diglib-1777-img-0011_100">
        <mets:FLocat LOCTYPE="URL" xlink:href="https://www.thomasgray.org/images/diglib/secondary/1777/0011.gif"/>
      </mets:file>
      <mets:file MIMETYPE="image/gif" ID="diglib-1777-img-0012_100">
        <mets:FLocat LOCTYPE="URL" xlink:href="https://www.thomasgray.org/images/diglib/secondary/1777/0012.gif"/>
      </mets:file>
      <mets:file MIMETYPE="image/gif" ID="diglib-1777-img-0013_100">
        <mets:FLocat LOCTYPE="URL" xlink:href="https://www.thomasgray.org/images/diglib/secondary/1777/0013.gif"/>
      </mets:file>
      <mets:file MIMETYPE="image/gif" ID="diglib-1777-img-0014_100">
        <mets:FLocat LOCTYPE="URL" xlink:href="https://www.thomasgray.org/images/diglib/secondary/1777/0014.gif"/>
      </mets:file>
      <mets:file MIMETYPE="image/gif" ID="diglib-1777-img-0015_100">
        <mets:FLocat LOCTYPE="URL" xlink:href="https://www.thomasgray.org/images/diglib/secondary/1777/0015.gif"/>
      </mets:file>
      <mets:file MIMETYPE="image/gif" ID="diglib-1777-img-0016_100">
        <mets:FLocat LOCTYPE="URL" xlink:href="https://www.thomasgray.org/images/diglib/secondary/1777/0016.gif"/>
      </mets:file>
      <mets:file MIMETYPE="image/gif" ID="diglib-1777-img-0017_100">
        <mets:FLocat LOCTYPE="URL" xlink:href="https://www.thomasgray.org/images/diglib/secondary/1777/0017.gif"/>
      </mets:file>
      <mets:file MIMETYPE="image/gif" ID="diglib-1777-img-0018_100">
        <mets:FLocat LOCTYPE="URL" xlink:href="https://www.thomasgray.org/images/diglib/secondary/1777/0018.gif"/>
      </mets:file>
      <mets:file MIMETYPE="image/gif" ID="diglib-1777-img-0019_100">
        <mets:FLocat LOCTYPE="URL" xlink:href="https://www.thomasgray.org/images/diglib/secondary/1777/0019.gif"/>
      </mets:file>
      <mets:file MIMETYPE="image/gif" ID="diglib-1777-img-0020_100">
        <mets:FLocat LOCTYPE="URL" xlink:href="https://www.thomasgray.org/images/diglib/secondary/1777/0020.gif"/>
      </mets:file>
      <mets:file MIMETYPE="image/gif" ID="diglib-1777-img-0021_100">
        <mets:FLocat LOCTYPE="URL" xlink:href="https://www.thomasgray.org/images/diglib/secondary/1777/0021.gif"/>
      </mets:file>
      <mets:file MIMETYPE="image/gif" ID="diglib-1777-img-0022_100">
        <mets:FLocat LOCTYPE="URL" xlink:href="https://www.thomasgray.org/images/diglib/secondary/1777/0022.gif"/>
      </mets:file>
      <mets:file MIMETYPE="image/gif" ID="diglib-1777-img-0023_100">
        <mets:FLocat LOCTYPE="URL" xlink:href="https://www.thomasgray.org/images/diglib/secondary/1777/0023.gif"/>
      </mets:file>
      <mets:file MIMETYPE="image/gif" ID="diglib-1777-img-0024_100">
        <mets:FLocat LOCTYPE="URL" xlink:href="https://www.thomasgray.org/images/diglib/secondary/1777/0024.gif"/>
      </mets:file>
      <mets:file MIMETYPE="image/gif" ID="diglib-1777-img-0025_100">
        <mets:FLocat LOCTYPE="URL" xlink:href="https://www.thomasgray.org/images/diglib/secondary/1777/0025.gif"/>
      </mets:file>
      <mets:file MIMETYPE="image/gif" ID="diglib-1777-img-0026_100">
        <mets:FLocat LOCTYPE="URL" xlink:href="https://www.thomasgray.org/images/diglib/secondary/1777/0026.gif"/>
      </mets:file>
      <mets:file MIMETYPE="image/gif" ID="diglib-1777-img-0027_100">
        <mets:FLocat LOCTYPE="URL" xlink:href="https://www.thomasgray.org/images/diglib/secondary/1777/0027.gif"/>
      </mets:file>
      <mets:file MIMETYPE="image/gif" ID="diglib-1777-img-0028_100">
        <mets:FLocat LOCTYPE="URL" xlink:href="https://www.thomasgray.org/images/diglib/secondary/1777/0028.gif"/>
      </mets:file>
      <mets:file MIMETYPE="image/gif" ID="diglib-1777-img-0029_100">
        <mets:FLocat LOCTYPE="URL" xlink:href="https://www.thomasgray.org/images/diglib/secondary/1777/0029.gif"/>
      </mets:file>
      <mets:file MIMETYPE="image/gif" ID="diglib-1777-img-0030_100">
        <mets:FLocat LOCTYPE="URL" xlink:href="https://www.thomasgray.org/images/diglib/secondary/1777/0030.gif"/>
      </mets:file>
      <mets:file MIMETYPE="image/gif" ID="diglib-1777-img-0031_100">
        <mets:FLocat LOCTYPE="URL" xlink:href="https://www.thomasgray.org/images/diglib/secondary/1777/0031.gif"/>
      </mets:file>
      <mets:file MIMETYPE="image/gif" ID="diglib-1777-img-0032_100">
        <mets:FLocat LOCTYPE="URL" xlink:href="https://www.thomasgray.org/images/diglib/secondary/1777/0032.gif"/>
      </mets:file>
      <mets:file MIMETYPE="image/gif" ID="diglib-1777-img-0033_100">
        <mets:FLocat LOCTYPE="URL" xlink:href="https://www.thomasgray.org/images/diglib/secondary/1777/0033.gif"/>
      </mets:file>
      <mets:file MIMETYPE="image/gif" ID="diglib-1777-img-0034_100">
        <mets:FLocat LOCTYPE="URL" xlink:href="https://www.thomasgray.org/images/diglib/secondary/1777/0034.gif"/>
      </mets:file>
      <mets:file MIMETYPE="image/gif" ID="diglib-1777-img-0035_100">
        <mets:FLocat LOCTYPE="URL" xlink:href="https://www.thomasgray.org/images/diglib/secondary/1777/0035.gif"/>
      </mets:file>
      <mets:file MIMETYPE="image/gif" ID="diglib-1777-img-0036_100">
        <mets:FLocat LOCTYPE="URL" xlink:href="https://www.thomasgray.org/images/diglib/secondary/1777/0036.gif"/>
      </mets:file>
      <mets:file MIMETYPE="image/gif" ID="diglib-1777-img-0037_100">
        <mets:FLocat LOCTYPE="URL" xlink:href="https://www.thomasgray.org/images/diglib/secondary/1777/0037.gif"/>
      </mets:file>
      <mets:file MIMETYPE="image/gif" ID="diglib-1777-img-0038_100">
        <mets:FLocat LOCTYPE="URL" xlink:href="https://www.thomasgray.org/images/diglib/secondary/1777/0038.gif"/>
      </mets:file>
      <mets:file MIMETYPE="image/gif" ID="diglib-1777-img-0039_100">
        <mets:FLocat LOCTYPE="URL" xlink:href="https://www.thomasgray.org/images/diglib/secondary/1777/0039.gif"/>
      </mets:file>
      <mets:file MIMETYPE="image/gif" ID="diglib-1777-img-0040_100">
        <mets:FLocat LOCTYPE="URL" xlink:href="https://www.thomasgray.org/images/diglib/secondary/1777/0040.gif"/>
      </mets:file>
      <mets:file MIMETYPE="image/gif" ID="diglib-1777-img-0041_100">
        <mets:FLocat LOCTYPE="URL" xlink:href="https://www.thomasgray.org/images/diglib/secondary/1777/0041.gif"/>
      </mets:file>
      <mets:file MIMETYPE="image/gif" ID="diglib-1777-img-0042_100">
        <mets:FLocat LOCTYPE="URL" xlink:href="https://www.thomasgray.org/images/diglib/secondary/1777/0042.gif"/>
      </mets:file>
      <mets:file MIMETYPE="image/gif" ID="diglib-1777-img-0043_100">
        <mets:FLocat LOCTYPE="URL" xlink:href="https://www.thomasgray.org/images/diglib/secondary/1777/0043.gif"/>
      </mets:file>
      <mets:file MIMETYPE="image/gif" ID="diglib-1777-img-0044_100">
        <mets:FLocat LOCTYPE="URL" xlink:href="https://www.thomasgray.org/images/diglib/secondary/1777/0044.gif"/>
      </mets:file>
      <mets:file MIMETYPE="image/gif" ID="diglib-1777-img-0045_100">
        <mets:FLocat LOCTYPE="URL" xlink:href="https://www.thomasgray.org/images/diglib/secondary/1777/0045.gif"/>
      </mets:file>
      <mets:file MIMETYPE="image/gif" ID="diglib-1777-img-0046_100">
        <mets:FLocat LOCTYPE="URL" xlink:href="https://www.thomasgray.org/images/diglib/secondary/1777/0046.gif"/>
      </mets:file>
      <mets:file MIMETYPE="image/gif" ID="diglib-1777-img-0047_100">
        <mets:FLocat LOCTYPE="URL" xlink:href="https://www.thomasgray.org/images/diglib/secondary/1777/0047.gif"/>
      </mets:file>
      <mets:file MIMETYPE="image/gif" ID="diglib-1777-img-0048_100">
        <mets:FLocat LOCTYPE="URL" xlink:href="https://www.thomasgray.org/images/diglib/secondary/1777/0048.gif"/>
      </mets:file>
      <mets:file MIMETYPE="image/gif" ID="diglib-1777-img-0049_100">
        <mets:FLocat LOCTYPE="URL" xlink:href="https://www.thomasgray.org/images/diglib/secondary/1777/0049.gif"/>
      </mets:file>
      <mets:file MIMETYPE="image/gif" ID="diglib-1777-img-0050_100">
        <mets:FLocat LOCTYPE="URL" xlink:href="https://www.thomasgray.org/images/diglib/secondary/1777/0050.gif"/>
      </mets:file>
      <mets:file MIMETYPE="image/gif" ID="diglib-1777-img-0051_100">
        <mets:FLocat LOCTYPE="URL" xlink:href="https://www.thomasgray.org/images/diglib/secondary/1777/0051.gif"/>
      </mets:file>
      <mets:file MIMETYPE="image/gif" ID="diglib-1777-img-0052_100">
        <mets:FLocat LOCTYPE="URL" xlink:href="https://www.thomasgray.org/images/diglib/secondary/1777/0052.gif"/>
      </mets:file>
      <mets:file MIMETYPE="image/gif" ID="diglib-1777-img-0053_100">
        <mets:FLocat LOCTYPE="URL" xlink:href="https://www.thomasgray.org/images/diglib/secondary/1777/0053.gif"/>
      </mets:file>
      <mets:file MIMETYPE="image/gif" ID="diglib-1777-img-0054_100">
        <mets:FLocat LOCTYPE="URL" xlink:href="https://www.thomasgray.org/images/diglib/secondary/1777/0054.gif"/>
      </mets:file>
      <mets:file MIMETYPE="image/gif" ID="diglib-1777-img-0055_100">
        <mets:FLocat LOCTYPE="URL" xlink:href="https://www.thomasgray.org/images/diglib/secondary/1777/0055.gif"/>
      </mets:file>
      <mets:file MIMETYPE="image/gif" ID="diglib-1777-img-0056_100">
        <mets:FLocat LOCTYPE="URL" xlink:href="https://www.thomasgray.org/images/diglib/secondary/1777/0056.gif"/>
      </mets:file>
      <mets:file MIMETYPE="image/gif" ID="diglib-1777-img-0057_100">
        <mets:FLocat LOCTYPE="URL" xlink:href="https://www.thomasgray.org/images/diglib/secondary/1777/0057.gif"/>
      </mets:file>
      <mets:file MIMETYPE="image/gif" ID="diglib-1777-img-0058_100">
        <mets:FLocat LOCTYPE="URL" xlink:href="https://www.thomasgray.org/images/diglib/secondary/1777/0058.gif"/>
      </mets:file>
      <mets:file MIMETYPE="image/gif" ID="diglib-1777-img-0059_100">
        <mets:FLocat LOCTYPE="URL" xlink:href="https://www.thomasgray.org/images/diglib/secondary/1777/0059.gif"/>
      </mets:file>
      <mets:file MIMETYPE="image/gif" ID="diglib-1777-img-0060_100">
        <mets:FLocat LOCTYPE="URL" xlink:href="https://www.thomasgray.org/images/diglib/secondary/1777/0060.gif"/>
      </mets:file>
      <mets:file MIMETYPE="image/gif" ID="diglib-1777-img-0061_100">
        <mets:FLocat LOCTYPE="URL" xlink:href="https://www.thomasgray.org/images/diglib/secondary/1777/0061.gif"/>
      </mets:file>
      <mets:file MIMETYPE="image/gif" ID="diglib-1777-img-0062_100">
        <mets:FLocat LOCTYPE="URL" xlink:href="https://www.thomasgray.org/images/diglib/secondary/1777/0062.gif"/>
      </mets:file>
      <mets:file MIMETYPE="image/gif" ID="diglib-1777-img-0063_100">
        <mets:FLocat LOCTYPE="URL" xlink:href="https://www.thomasgray.org/images/diglib/secondary/1777/0063.gif"/>
      </mets:file>
      <mets:file MIMETYPE="image/gif" ID="diglib-1777-img-0064_100">
        <mets:FLocat LOCTYPE="URL" xlink:href="https://www.thomasgray.org/images/diglib/secondary/1777/0064.gif"/>
      </mets:file>
    </mets:fileGrp>
  </mets:fileSec>

  <mets:structMap TYPE="LOGICAL">
    <mets:div ID="diglib-1777-log-0000" DMDID="diglib-1777-dmd-0000" ADMID="diglib-1777-amd-0000" TYPE=" ">
      <mets:div ID="diglib-1777-log-0001" LABEL="Letter to W. Mason, A.M." TYPE="TitlePage"/>
      <mets:div ID="diglib-1777-log-0002" LABEL="A Letter to W. Mason, A.M. precentor of York, concerning his edition of Mr. Gray's Poems. And the Practices of Booksellers" TYPE="TitlePage"/>
      <mets:div ID="diglib-1777-log-0003" LABEL="Letter to William Mason, A.M." TYPE="TextSection"/>
      <mets:div ID="diglib-1777-log-0004" LABEL="Appendix" TYPE="Appendix"/>
      <mets:div ID="diglib-1777-log-0005" LABEL="The Death of Hoel" TYPE="TextSection"/>
      <mets:div ID="diglib-1777-log-0006" LABEL="On the Death of Richard West" TYPE="TextSection"/>
      <mets:div ID="diglib-1777-log-0007" LABEL="Epitaph on Sir William Williams" TYPE="TextSection"/>
    </mets:div>
  </mets:structMap>

  <mets:structMap TYPE="PHYSICAL">
    <mets:div ID="diglib-1777-phys-0000" TYPE="physSequence">
      <mets:div ID="diglib-1777-phys-0001" ORDER="1" TYPE="page" ORDERLABEL="[1]">
        <mets:fptr FILEID="diglib-1777-img-0001_100"/>
      </mets:div>
      <mets:div ID="diglib-1777-phys-0002" ORDER="2" TYPE="page" ORDERLABEL="[2]">
        <mets:fptr FILEID="diglib-1777-img-0002_100"/>
      </mets:div>
      <mets:div ID="diglib-1777-phys-0003" ORDER="3" TYPE="page" ORDERLABEL="[3]">
        <mets:fptr FILEID="diglib-1777-img-0003_100"/>
      </mets:div>
      <mets:div ID="diglib-1777-phys-0004" ORDER="4" TYPE="page" ORDERLABEL="[4]">
        <mets:fptr FILEID="diglib-1777-img-0004_100"/>
      </mets:div>
      <mets:div ID="diglib-1777-phys-0005" ORDER="5" TYPE="page" ORDERLABEL="[5]">
        <mets:fptr FILEID="diglib-1777-img-0005_100"/>
      </mets:div>
      <mets:div ID="diglib-1777-phys-0006" ORDER="6" TYPE="page" ORDERLABEL="6">
        <mets:fptr FILEID="diglib-1777-img-0006_100"/>
      </mets:div>
      <mets:div ID="diglib-1777-phys-0007" ORDER="7" TYPE="page" ORDERLABEL="7">
        <mets:fptr FILEID="diglib-1777-img-0007_100"/>
      </mets:div>
      <mets:div ID="diglib-1777-phys-0008" ORDER="8" TYPE="page" ORDERLABEL="8">
        <mets:fptr FILEID="diglib-1777-img-0008_100"/>
      </mets:div>
      <mets:div ID="diglib-1777-phys-0009" ORDER="9" TYPE="page" ORDERLABEL="9">
        <mets:fptr FILEID="diglib-1777-img-0009_100"/>
      </mets:div>
      <mets:div ID="diglib-1777-phys-0010" ORDER="10" TYPE="page" ORDERLABEL="10">
        <mets:fptr FILEID="diglib-1777-img-0010_100"/>
      </mets:div>
      <mets:div ID="diglib-1777-phys-0011" ORDER="11" TYPE="page" ORDERLABEL="11">
        <mets:fptr FILEID="diglib-1777-img-0011_100"/>
      </mets:div>
      <mets:div ID="diglib-1777-phys-0012" ORDER="12" TYPE="page" ORDERLABEL="12">
        <mets:fptr FILEID="diglib-1777-img-0012_100"/>
      </mets:div>
      <mets:div ID="diglib-1777-phys-0013" ORDER="13" TYPE="page" ORDERLABEL="13">
        <mets:fptr FILEID="diglib-1777-img-0013_100"/>
      </mets:div>
      <mets:div ID="diglib-1777-phys-0014" ORDER="14" TYPE="page" ORDERLABEL="14">
        <mets:fptr FILEID="diglib-1777-img-0014_100"/>
      </mets:div>
      <mets:div ID="diglib-1777-phys-0015" ORDER="15" TYPE="page" ORDERLABEL="15">
        <mets:fptr FILEID="diglib-1777-img-0015_100"/>
      </mets:div>
      <mets:div ID="diglib-1777-phys-0016" ORDER="16" TYPE="page" ORDERLABEL="16">
        <mets:fptr FILEID="diglib-1777-img-0016_100"/>
      </mets:div>
      <mets:div ID="diglib-1777-phys-0017" ORDER="17" TYPE="page" ORDERLABEL="17">
        <mets:fptr FILEID="diglib-1777-img-0017_100"/>
      </mets:div>
      <mets:div ID="diglib-1777-phys-0018" ORDER="18" TYPE="page" ORDERLABEL="18">
        <mets:fptr FILEID="diglib-1777-img-0018_100"/>
      </mets:div>
      <mets:div ID="diglib-1777-phys-0019" ORDER="19" TYPE="page" ORDERLABEL="19">
        <mets:fptr FILEID="diglib-1777-img-0019_100"/>
      </mets:div>
      <mets:div ID="diglib-1777-phys-0020" ORDER="20" TYPE="page" ORDERLABEL="20">
        <mets:fptr FILEID="diglib-1777-img-0020_100"/>
      </mets:div>
      <mets:div ID="diglib-1777-phys-0021" ORDER="21" TYPE="page" ORDERLABEL="21">
        <mets:fptr FILEID="diglib-1777-img-0021_100"/>
      </mets:div>
      <mets:div ID="diglib-1777-phys-0022" ORDER="22" TYPE="page" ORDERLABEL="22">
        <mets:fptr FILEID="diglib-1777-img-0022_100"/>
      </mets:div>
      <mets:div ID="diglib-1777-phys-0023" ORDER="23" TYPE="page" ORDERLABEL="23">
        <mets:fptr FILEID="diglib-1777-img-0023_100"/>
      </mets:div>
      <mets:div ID="diglib-1777-phys-0024" ORDER="24" TYPE="page" ORDERLABEL="24">
        <mets:fptr FILEID="diglib-1777-img-0024_100"/>
      </mets:div>
      <mets:div ID="diglib-1777-phys-0025" ORDER="25" TYPE="page" ORDERLABEL="25">
        <mets:fptr FILEID="diglib-1777-img-0025_100"/>
      </mets:div>
      <mets:div ID="diglib-1777-phys-0026" ORDER="26" TYPE="page" ORDERLABEL="26">
        <mets:fptr FILEID="diglib-1777-img-0026_100"/>
      </mets:div>
      <mets:div ID="diglib-1777-phys-0027" ORDER="27" TYPE="page" ORDERLABEL="27">
        <mets:fptr FILEID="diglib-1777-img-0027_100"/>
      </mets:div>
      <mets:div ID="diglib-1777-phys-0028" ORDER="28" TYPE="page" ORDERLABEL="28">
        <mets:fptr FILEID="diglib-1777-img-0028_100"/>
      </mets:div>
      <mets:div ID="diglib-1777-phys-0029" ORDER="29" TYPE="page" ORDERLABEL="29">
        <mets:fptr FILEID="diglib-1777-img-0029_100"/>
      </mets:div>
      <mets:div ID="diglib-1777-phys-0030" ORDER="30" TYPE="page" ORDERLABEL="30">
        <mets:fptr FILEID="diglib-1777-img-0030_100"/>
      </mets:div>
      <mets:div ID="diglib-1777-phys-0031" ORDER="31" TYPE="page" ORDERLABEL="31">
        <mets:fptr FILEID="diglib-1777-img-0031_100"/>
      </mets:div>
      <mets:div ID="diglib-1777-phys-0032" ORDER="32" TYPE="page" ORDERLABEL="32">
        <mets:fptr FILEID="diglib-1777-img-0032_100"/>
      </mets:div>
      <mets:div ID="diglib-1777-phys-0033" ORDER="33" TYPE="page" ORDERLABEL="33">
        <mets:fptr FILEID="diglib-1777-img-0033_100"/>
      </mets:div>
      <mets:div ID="diglib-1777-phys-0034" ORDER="34" TYPE="page" ORDERLABEL="34">
        <mets:fptr FILEID="diglib-1777-img-0034_100"/>
      </mets:div>
      <mets:div ID="diglib-1777-phys-0035" ORDER="35" TYPE="page" ORDERLABEL="35">
        <mets:fptr FILEID="diglib-1777-img-0035_100"/>
      </mets:div>
      <mets:div ID="diglib-1777-phys-0036" ORDER="36" TYPE="page" ORDERLABEL="36">
        <mets:fptr FILEID="diglib-1777-img-0036_100"/>
      </mets:div>
      <mets:div ID="diglib-1777-phys-0037" ORDER="37" TYPE="page" ORDERLABEL="37">
        <mets:fptr FILEID="diglib-1777-img-0037_100"/>
      </mets:div>
      <mets:div ID="diglib-1777-phys-0038" ORDER="38" TYPE="page" ORDERLABEL="38">
        <mets:fptr FILEID="diglib-1777-img-0038_100"/>
      </mets:div>
      <mets:div ID="diglib-1777-phys-0039" ORDER="39" TYPE="page" ORDERLABEL="39">
        <mets:fptr FILEID="diglib-1777-img-0039_100"/>
      </mets:div>
      <mets:div ID="diglib-1777-phys-0040" ORDER="40" TYPE="page" ORDERLABEL="40">
        <mets:fptr FILEID="diglib-1777-img-0040_100"/>
      </mets:div>
      <mets:div ID="diglib-1777-phys-0041" ORDER="41" TYPE="page" ORDERLABEL="41">
        <mets:fptr FILEID="diglib-1777-img-0041_100"/>
      </mets:div>
      <mets:div ID="diglib-1777-phys-0042" ORDER="42" TYPE="page" ORDERLABEL="42">
        <mets:fptr FILEID="diglib-1777-img-0042_100"/>
      </mets:div>
      <mets:div ID="diglib-1777-phys-0043" ORDER="43" TYPE="page" ORDERLABEL="43">
        <mets:fptr FILEID="diglib-1777-img-0043_100"/>
      </mets:div>
      <mets:div ID="diglib-1777-phys-0044" ORDER="44" TYPE="page" ORDERLABEL="44">
        <mets:fptr FILEID="diglib-1777-img-0044_100"/>
      </mets:div>
      <mets:div ID="diglib-1777-phys-0045" ORDER="45" TYPE="page" ORDERLABEL="45">
        <mets:fptr FILEID="diglib-1777-img-0045_100"/>
      </mets:div>
      <mets:div ID="diglib-1777-phys-0046" ORDER="46" TYPE="page" ORDERLABEL="46">
        <mets:fptr FILEID="diglib-1777-img-0046_100"/>
      </mets:div>
      <mets:div ID="diglib-1777-phys-0047" ORDER="47" TYPE="page" ORDERLABEL="47">
        <mets:fptr FILEID="diglib-1777-img-0047_100"/>
      </mets:div>
      <mets:div ID="diglib-1777-phys-0048" ORDER="48" TYPE="page" ORDERLABEL="48">
        <mets:fptr FILEID="diglib-1777-img-0048_100"/>
      </mets:div>
      <mets:div ID="diglib-1777-phys-0049" ORDER="49" TYPE="page" ORDERLABEL="49">
        <mets:fptr FILEID="diglib-1777-img-0049_100"/>
      </mets:div>
      <mets:div ID="diglib-1777-phys-0050" ORDER="50" TYPE="page" ORDERLABEL="50">
        <mets:fptr FILEID="diglib-1777-img-0050_100"/>
      </mets:div>
      <mets:div ID="diglib-1777-phys-0051" ORDER="51" TYPE="page" ORDERLABEL="51">
        <mets:fptr FILEID="diglib-1777-img-0051_100"/>
      </mets:div>
      <mets:div ID="diglib-1777-phys-0052" ORDER="52" TYPE="page" ORDERLABEL="52">
        <mets:fptr FILEID="diglib-1777-img-0052_100"/>
      </mets:div>
      <mets:div ID="diglib-1777-phys-0053" ORDER="53" TYPE="page" ORDERLABEL="53">
        <mets:fptr FILEID="diglib-1777-img-0053_100"/>
      </mets:div>
      <mets:div ID="diglib-1777-phys-0054" ORDER="54" TYPE="page" ORDERLABEL="54">
        <mets:fptr FILEID="diglib-1777-img-0054_100"/>
      </mets:div>
      <mets:div ID="diglib-1777-phys-0055" ORDER="55" TYPE="page" ORDERLABEL="55">
        <mets:fptr FILEID="diglib-1777-img-0055_100"/>
      </mets:div>
      <mets:div ID="diglib-1777-phys-0056" ORDER="56" TYPE="page" ORDERLABEL="56">
        <mets:fptr FILEID="diglib-1777-img-0056_100"/>
      </mets:div>
      <mets:div ID="diglib-1777-phys-0057" ORDER="57" TYPE="page" ORDERLABEL="[57]">
        <mets:fptr FILEID="diglib-1777-img-0057_100"/>
      </mets:div>
      <mets:div ID="diglib-1777-phys-0058" ORDER="58" TYPE="page" ORDERLABEL="58">
        <mets:fptr FILEID="diglib-1777-img-0058_100"/>
      </mets:div>
      <mets:div ID="diglib-1777-phys-0059" ORDER="59" TYPE="page" ORDERLABEL="59">
        <mets:fptr FILEID="diglib-1777-img-0059_100"/>
      </mets:div>
      <mets:div ID="diglib-1777-phys-0060" ORDER="60" TYPE="page" ORDERLABEL="60">
        <mets:fptr FILEID="diglib-1777-img-0060_100"/>
      </mets:div>
      <mets:div ID="diglib-1777-phys-0061" ORDER="61" TYPE="page" ORDERLABEL="61">
        <mets:fptr FILEID="diglib-1777-img-0061_100"/>
      </mets:div>
      <mets:div ID="diglib-1777-phys-0062" ORDER="62" TYPE="page" ORDERLABEL="62">
        <mets:fptr FILEID="diglib-1777-img-0062_100"/>
      </mets:div>
      <mets:div ID="diglib-1777-phys-0063" ORDER="63" TYPE="page" ORDERLABEL="63">
        <mets:fptr FILEID="diglib-1777-img-0063_100"/>
      </mets:div>
      <mets:div ID="diglib-1777-phys-0064" ORDER="64" TYPE="page" ORDERLABEL="64">
        <mets:fptr FILEID="diglib-1777-img-0064_100"/>
      </mets:div>
    </mets:div>
  </mets:structMap>

  <mets:structLink>
    <mets:smLink xlink:from="diglib-1777-log-0000" xlink:to="diglib-1777-phys-0000"/>
    <mets:smLink xlink:from="diglib-1777-log-0001" xlink:to="diglib-1777-phys-0001"/>
    <mets:smLink xlink:from="diglib-1777-log-0002" xlink:to="diglib-1777-phys-0003"/>
    <mets:smLink xlink:from="diglib-1777-log-0003" xlink:to="diglib-1777-phys-0005"/>
    <mets:smLink xlink:from="diglib-1777-log-0004" xlink:to="diglib-1777-phys-0057"/>
    <mets:smLink xlink:from="diglib-1777-log-0005" xlink:to="diglib-1777-phys-0060"/>
    <mets:smLink xlink:from="diglib-1777-log-0006" xlink:to="diglib-1777-phys-0061"/>
    <mets:smLink xlink:from="diglib-1777-log-0007" xlink:to="diglib-1777-phys-0062"/>
  </mets:structLink>

</mets:mets>