<?xml version="1.0" encoding="UTF-8"?>
<!DOCTYPE mets:mets [
  <!ENTITY AElig  '&#xC6;'>
  <!ENTITY Eacute '&#xC9;'>
  <!ENTITY eacute '&#xE9;'>
  <!ENTITY egrave '&#xE8;'>
  <!ENTITY ccedil '&#xE7;'>
  <!ENTITY ecirc  '&#xEA;'>
  <!ENTITY aelig  '&#xE6;'>
  <!ENTITY copy   '&#169;'>
  <!ENTITY deg    '&#176;'>
  <!ENTITY nbsp   '&#160;'>
  <!ENTITY ouml   '&#246;'>
]>
<mets:mets xmlns:xsi="http://www.w3.org/2001/XMLSchema-instance"
  xmlns:xlink="http://www.w3.org/1999/xlink"
  xmlns:mets="http://www.loc.gov/METS/"
  xsi:schemaLocation="http://www.loc.gov/METS/ http://www.loc.gov/mets/mets.xsd">
<!-- See e.g. <http://dfg-viewer.de/show/?tx_dlf%5Bid%5D=https%3A%2F%2Fwww.thomasgray.org%2Fimages%2Fdiglib%2Fmets%2F1787.xml&no_cache=1> -->

  <mets:dmdSec ID="diglib-1787-dmd-0000">
    <mets:mdWrap MIMETYPE="text/xml" MDTYPE="MODS">
      <mets:xmlData>
        <mods:mods xmlns:mods="http://www.loc.gov/mods/v3" version="3.3"
          xsi:schemaLocation="http://www.loc.gov/mods/v3 http://www.loc.gov/standards/mods/v3/mods-3-3.xsd">
          <mods:identifier type="urn">urn:x-thomasgrayarchive:grayt.1787</mods:identifier>
          <mods:titleInfo>
            <mods:title>The Grave; By Robert Blair. To which is added Gray's Elegy in a Country Church Yard. With Notes Moral, Critical, and Explanatory.
            </mods:title>
          </mods:titleInfo>
          <mods:typeOfResource>still image</mods:typeOfResource>
          <mods:name type="personal" authority="lcnaf">
            <mods:displayForm>Blair, Robert, 1699-1746</mods:displayForm>
            <mods:role>
              <mods:roleTerm type="text">author</mods:roleTerm>
              <mods:roleTerm authority="marcrelator" type="code">aut</mods:roleTerm>
            </mods:role>
          </mods:name>
          <mods:name type="personal" authority="lcnaf">
            <mods:displayForm>Gray, Thomas, 1716-1771</mods:displayForm>
            <mods:role>
              <mods:roleTerm type="text">author</mods:roleTerm>
              <mods:roleTerm authority="marcrelator" type="code">aut</mods:roleTerm>
            </mods:role>
          </mods:name>
          <mods:name type="personal" authority="lcnaf">
            <mods:displayForm>[Wright, George, Esq.]</mods:displayForm>
            <mods:role>
              <mods:roleTerm type="text">editor</mods:roleTerm>
              <mods:roleTerm authority="marcrelator" type="code">edt</mods:roleTerm>
            </mods:role>
          </mods:name>
          <mods:originInfo>
            <mods:publisher>
               London: Printed for Scatcherd &amp; Whitaker..., [1787]. 
            </mods:publisher>                        
            <mods:dateCaptured>
              06/02/2006
            </mods:dateCaptured>
            <mods:dateIssued encoding="iso8601" keyDate="yes">1787?</mods:dateIssued>
          </mods:originInfo>
          <mods:physicalDescription>
            <mods:extent>
              [2],52p.; 4&deg;.
            </mods:extent>
            <mods:note type="physical description">
              Title vignette.
            </mods:note>
            <mods:digitalOrigin>reformatted digital</mods:digitalOrigin>
          </mods:physicalDescription>
          <mods:location>
            <mods:physicalLocation>
              Bodleian Library, University of Oxford
            </mods:physicalLocation>              
            <mods:shelfLocator>
               G. Pamph. 1264 (23/24)
            </mods:shelfLocator>
          </mods:location>
          <mods:relatedItem type="isReferencedBy">
            <mods:note type="citation/reference">
              Northup 533
            </mods:note>
          </mods:relatedItem>
          <mods:relatedItem type="isReferencedBy">
            <mods:note type="citation/reference">
              ESTC T74312.
            </mods:note>
          </mods:relatedItem>
          <mods:accessCondition>
            Copyright &copy; 2006 Bodleian Library, University of Oxford; access to digitized documents is granted strictly for non-commercial educational,  research and private purposes only. 
          </mods:accessCondition>
          <mods:recordInfo>
            <mods:recordIdentifier source="TGA">1787</mods:recordIdentifier>
          </mods:recordInfo>
        </mods:mods>
      </mets:xmlData>
    </mets:mdWrap>
  </mets:dmdSec>

  <mets:amdSec ID="diglib-1787-amd-0000">
    <mets:rightsMD ID="diglib1787-amd-rights-0000">
      <mets:mdWrap MIMETYPE="text/xml" MDTYPE="OTHER" OTHERMDTYPE="DVRIGHTS">
        <mets:xmlData>
          <dv:rights xmlns:dv="http://dfg-viewer.de/">
            <dv:owner>Thomas Gray Archive</dv:owner>
            <dv:ownerContact>mailto:info@thomasgray.org</dv:ownerContact>
            <dv:ownerLogo>https://www.thomasgray.org/images/GrayTh1716_NPG.jpg</dv:ownerLogo>
            <dv:ownerSiteURL>https://www.thomasgray.org/</dv:ownerSiteURL>
          </dv:rights>
        </mets:xmlData>
      </mets:mdWrap>
    </mets:rightsMD>
    <mets:digiprovMD ID="diglib-1787-amd-digiprov-0000">
      <mets:mdWrap MIMETYPE="text/xml" MDTYPE="OTHER" OTHERMDTYPE="DVLINKS">
        <mets:xmlData>
          <dv:links xmlns:dv="http://dfg-viewer.de/">
            <dv:reference>https://www.thomasgray.org/texts/diglib/primary/1787#record</dv:reference>
            <dv:presentation>https://www.thomasgray.org/texts/diglib/primary/1787</dv:presentation>
          </dv:links>
        </mets:xmlData>
      </mets:mdWrap>
    </mets:digiprovMD>
  </mets:amdSec>

  <mets:fileSec>
    <mets:fileGrp USE="DEFAULT">
      <mets:file ID="diglib-1787-img-bdp0002">
        <mets:FLocat LOCTYPE="URL" xlink:href="https://www.thomasgray.org/images/diglib/primary/1787/bdp0002.PNG"/>
      </mets:file>
      <mets:file ID="diglib-1787-img-bdp0003">
        <mets:FLocat LOCTYPE="URL" xlink:href="https://www.thomasgray.org/images/diglib/primary/1787/bdp0003.PNG"/>
      </mets:file>
      <mets:file ID="diglib-1787-img-bdp0004">
        <mets:FLocat LOCTYPE="URL" xlink:href="https://www.thomasgray.org/images/diglib/primary/1787/bdp0004.PNG"/>
      </mets:file>
      <mets:file ID="diglib-1787-img-bdp0005">
        <mets:FLocat LOCTYPE="URL" xlink:href="https://www.thomasgray.org/images/diglib/primary/1787/bdp0005.PNG"/>
      </mets:file>
      <mets:file ID="diglib-1787-img-bdp0006">
        <mets:FLocat LOCTYPE="URL" xlink:href="https://www.thomasgray.org/images/diglib/primary/1787/bdp0006.PNG"/>
      </mets:file>
      <mets:file ID="diglib-1787-img-bdp0007">
        <mets:FLocat LOCTYPE="URL" xlink:href="https://www.thomasgray.org/images/diglib/primary/1787/bdp0007.PNG"/>
      </mets:file>
      <mets:file ID="diglib-1787-img-bdp0008">
        <mets:FLocat LOCTYPE="URL" xlink:href="https://www.thomasgray.org/images/diglib/primary/1787/bdp0008.PNG"/>
      </mets:file>
      <mets:file ID="diglib-1787-img-bdp0009">
        <mets:FLocat LOCTYPE="URL" xlink:href="https://www.thomasgray.org/images/diglib/primary/1787/bdp0009.PNG"/>
      </mets:file>
      <mets:file ID="diglib-1787-img-bdp0010">
        <mets:FLocat LOCTYPE="URL" xlink:href="https://www.thomasgray.org/images/diglib/primary/1787/bdp0010.PNG"/>
      </mets:file>
      <mets:file ID="diglib-1787-img-bdp0011">
        <mets:FLocat LOCTYPE="URL" xlink:href="https://www.thomasgray.org/images/diglib/primary/1787/bdp0011.PNG"/>
      </mets:file>
      <mets:file ID="diglib-1787-img-bdp0012">
        <mets:FLocat LOCTYPE="URL" xlink:href="https://www.thomasgray.org/images/diglib/primary/1787/bdp0012.PNG"/>
      </mets:file>
      <mets:file ID="diglib-1787-img-bdp0013">
        <mets:FLocat LOCTYPE="URL" xlink:href="https://www.thomasgray.org/images/diglib/primary/1787/bdp0013.PNG"/>
      </mets:file>
      <mets:file ID="diglib-1787-img-bdp0014">
        <mets:FLocat LOCTYPE="URL" xlink:href="https://www.thomasgray.org/images/diglib/primary/1787/bdp0014.PNG"/>
      </mets:file>
      <mets:file ID="diglib-1787-img-bdp0015">
        <mets:FLocat LOCTYPE="URL" xlink:href="https://www.thomasgray.org/images/diglib/primary/1787/bdp0015.PNG"/>
      </mets:file>
      <mets:file ID="diglib-1787-img-bdp0016">
        <mets:FLocat LOCTYPE="URL" xlink:href="https://www.thomasgray.org/images/diglib/primary/1787/bdp0016.PNG"/>
      </mets:file>
      <mets:file ID="diglib-1787-img-bdp0017">
        <mets:FLocat LOCTYPE="URL" xlink:href="https://www.thomasgray.org/images/diglib/primary/1787/bdp0017.PNG"/>
      </mets:file>
      <mets:file ID="diglib-1787-img-bdp0018">
        <mets:FLocat LOCTYPE="URL" xlink:href="https://www.thomasgray.org/images/diglib/primary/1787/bdp0018.PNG"/>
      </mets:file>
      <mets:file ID="diglib-1787-img-bdp0019">
        <mets:FLocat LOCTYPE="URL" xlink:href="https://www.thomasgray.org/images/diglib/primary/1787/bdp0019.PNG"/>
      </mets:file>
      <mets:file ID="diglib-1787-img-bdp0020">
        <mets:FLocat LOCTYPE="URL" xlink:href="https://www.thomasgray.org/images/diglib/primary/1787/bdp0020.PNG"/>
      </mets:file>
      <mets:file ID="diglib-1787-img-bdp0021">
        <mets:FLocat LOCTYPE="URL" xlink:href="https://www.thomasgray.org/images/diglib/primary/1787/bdp0021.PNG"/>
      </mets:file>
      <mets:file ID="diglib-1787-img-bdp0022">
        <mets:FLocat LOCTYPE="URL" xlink:href="https://www.thomasgray.org/images/diglib/primary/1787/bdp0022.PNG"/>
      </mets:file>
      <mets:file ID="diglib-1787-img-bdp0023">
        <mets:FLocat LOCTYPE="URL" xlink:href="https://www.thomasgray.org/images/diglib/primary/1787/bdp0023.PNG"/>
      </mets:file>
      <mets:file ID="diglib-1787-img-bdp0024">
        <mets:FLocat LOCTYPE="URL" xlink:href="https://www.thomasgray.org/images/diglib/primary/1787/bdp0024.PNG"/>
      </mets:file>
      <mets:file ID="diglib-1787-img-bdp0025">
        <mets:FLocat LOCTYPE="URL" xlink:href="https://www.thomasgray.org/images/diglib/primary/1787/bdp0025.PNG"/>
      </mets:file>
      <mets:file ID="diglib-1787-img-bdp0026">
        <mets:FLocat LOCTYPE="URL" xlink:href="https://www.thomasgray.org/images/diglib/primary/1787/bdp0026.PNG"/>
      </mets:file>
      <mets:file ID="diglib-1787-img-bdp0027">
        <mets:FLocat LOCTYPE="URL" xlink:href="https://www.thomasgray.org/images/diglib/primary/1787/bdp0027.PNG"/>
      </mets:file>
      <mets:file ID="diglib-1787-img-bdp0028">
        <mets:FLocat LOCTYPE="URL" xlink:href="https://www.thomasgray.org/images/diglib/primary/1787/bdp0028.PNG"/>
      </mets:file>
      <mets:file ID="diglib-1787-img-bdp0029">
        <mets:FLocat LOCTYPE="URL" xlink:href="https://www.thomasgray.org/images/diglib/primary/1787/bdp0029.PNG"/>
      </mets:file>
      <mets:file ID="diglib-1787-img-bdp0030">
        <mets:FLocat LOCTYPE="URL" xlink:href="https://www.thomasgray.org/images/diglib/primary/1787/bdp0030.PNG"/>
      </mets:file>
      <mets:file ID="diglib-1787-img-bdp0031">
        <mets:FLocat LOCTYPE="URL" xlink:href="https://www.thomasgray.org/images/diglib/primary/1787/bdp0031.PNG"/>
      </mets:file>
      <mets:file ID="diglib-1787-img-bdp0032">
        <mets:FLocat LOCTYPE="URL" xlink:href="https://www.thomasgray.org/images/diglib/primary/1787/bdp0032.PNG"/>
      </mets:file>
      <mets:file ID="diglib-1787-img-bdp0033">
        <mets:FLocat LOCTYPE="URL" xlink:href="https://www.thomasgray.org/images/diglib/primary/1787/bdp0033.PNG"/>
      </mets:file>
      <mets:file ID="diglib-1787-img-bdp0034">
        <mets:FLocat LOCTYPE="URL" xlink:href="https://www.thomasgray.org/images/diglib/primary/1787/bdp0034.PNG"/>
      </mets:file>
      <mets:file ID="diglib-1787-img-bdp0035">
        <mets:FLocat LOCTYPE="URL" xlink:href="https://www.thomasgray.org/images/diglib/primary/1787/bdp0035.PNG"/>
      </mets:file>
      <mets:file ID="diglib-1787-img-bdp0036">
        <mets:FLocat LOCTYPE="URL" xlink:href="https://www.thomasgray.org/images/diglib/primary/1787/bdp0036.PNG"/>
      </mets:file>
      <mets:file ID="diglib-1787-img-bdp0037">
        <mets:FLocat LOCTYPE="URL" xlink:href="https://www.thomasgray.org/images/diglib/primary/1787/bdp0037.PNG"/>
      </mets:file>
      <mets:file ID="diglib-1787-img-bdp0038">
        <mets:FLocat LOCTYPE="URL" xlink:href="https://www.thomasgray.org/images/diglib/primary/1787/bdp0038.PNG"/>
      </mets:file>
      <mets:file ID="diglib-1787-img-bdp0039">
        <mets:FLocat LOCTYPE="URL" xlink:href="https://www.thomasgray.org/images/diglib/primary/1787/bdp0039.PNG"/>
      </mets:file>
      <mets:file ID="diglib-1787-img-bdp0040">
        <mets:FLocat LOCTYPE="URL" xlink:href="https://www.thomasgray.org/images/diglib/primary/1787/bdp0040.PNG"/>
      </mets:file>
      <mets:file ID="diglib-1787-img-bdp0041">
        <mets:FLocat LOCTYPE="URL" xlink:href="https://www.thomasgray.org/images/diglib/primary/1787/bdp0041.PNG"/>
      </mets:file>
      <mets:file ID="diglib-1787-img-bdp0042">
        <mets:FLocat LOCTYPE="URL" xlink:href="https://www.thomasgray.org/images/diglib/primary/1787/bdp0042.PNG"/>
      </mets:file>
      <mets:file ID="diglib-1787-img-bdp0043">
        <mets:FLocat LOCTYPE="URL" xlink:href="https://www.thomasgray.org/images/diglib/primary/1787/bdp0043.PNG"/>
      </mets:file>
      <mets:file ID="diglib-1787-img-bdp0044">
        <mets:FLocat LOCTYPE="URL" xlink:href="https://www.thomasgray.org/images/diglib/primary/1787/bdp0044.PNG"/>
      </mets:file>
      <mets:file ID="diglib-1787-img-bdp0045">
        <mets:FLocat LOCTYPE="URL" xlink:href="https://www.thomasgray.org/images/diglib/primary/1787/bdp0045.PNG"/>
      </mets:file>
      <mets:file ID="diglib-1787-img-bdp0046">
        <mets:FLocat LOCTYPE="URL" xlink:href="https://www.thomasgray.org/images/diglib/primary/1787/bdp0046.PNG"/>
      </mets:file>
      <mets:file ID="diglib-1787-img-bdp0047">
        <mets:FLocat LOCTYPE="URL" xlink:href="https://www.thomasgray.org/images/diglib/primary/1787/bdp0047.PNG"/>
      </mets:file>
      <mets:file ID="diglib-1787-img-bdp0048">
        <mets:FLocat LOCTYPE="URL" xlink:href="https://www.thomasgray.org/images/diglib/primary/1787/bdp0048.PNG"/>
      </mets:file>
      <mets:file ID="diglib-1787-img-bdp0049">
        <mets:FLocat LOCTYPE="URL" xlink:href="https://www.thomasgray.org/images/diglib/primary/1787/bdp0049.PNG"/>
      </mets:file>
      <mets:file ID="diglib-1787-img-bdp0050">
        <mets:FLocat LOCTYPE="URL" xlink:href="https://www.thomasgray.org/images/diglib/primary/1787/bdp0050.PNG"/>
      </mets:file>
      <mets:file ID="diglib-1787-img-bdp0051">
        <mets:FLocat LOCTYPE="URL" xlink:href="https://www.thomasgray.org/images/diglib/primary/1787/bdp0051.PNG"/>
      </mets:file>
      <mets:file ID="diglib-1787-img-bdp0052">
        <mets:FLocat LOCTYPE="URL" xlink:href="https://www.thomasgray.org/images/diglib/primary/1787/bdp0052.PNG"/>
      </mets:file>
      <mets:file ID="diglib-1787-img-bdp0053">
        <mets:FLocat LOCTYPE="URL" xlink:href="https://www.thomasgray.org/images/diglib/primary/1787/bdp0053.PNG"/>
      </mets:file>
      <mets:file ID="diglib-1787-img-bdp0054">
        <mets:FLocat LOCTYPE="URL" xlink:href="https://www.thomasgray.org/images/diglib/primary/1787/bdp0054.PNG"/>
      </mets:file>
      <mets:file ID="diglib-1787-img-bdp0055">
        <mets:FLocat LOCTYPE="URL" xlink:href="https://www.thomasgray.org/images/diglib/primary/1787/bdp0055.PNG"/>
      </mets:file>
    </mets:fileGrp>
    <mets:fileGrp USE="DOWNLOAD">
      <mets:file ID="diglib-1787-pdf" MIMETYPE="application/pdf">
        <mets:FLocat LOCTYPE="URL" xlink:href="https://www.thomasgray.org/images/diglib/primary/1787/1787.pdf"/>
      </mets:file>
    </mets:fileGrp>
  </mets:fileSec>

  <mets:structMap TYPE="LOGICAL">
    <mets:div ID="diglib-1787-log-0000" DMDID="diglib-1787-dmd-0000" ADMID="diglib-1787-amd-0000" TYPE=" ">
      <mets:fptr FILEID="diglib-1787-pdf"/>
      <mets:div ID="diglib-1787-log-0001" LABEL="The Grave; By Robert Blair..." TYPE="TitlePage"/>
      <mets:div ID="diglib-1787-log-0002" LABEL="Preface" TYPE="DedicationForewordIntro"/>
      <mets:div ID="diglib-1787-log-0003" LABEL="The Grave, part the first" TYPE="TextSection"/>
      <mets:div ID="diglib-1787-log-0004" LABEL="The Grave, part the second" TYPE="TextSection"/>
      <mets:div ID="diglib-1787-log-0005" LABEL="An Elegy written in a Country Church-yard" TYPE="TextSection"/>
    </mets:div>
  </mets:structMap>

  <mets:structMap TYPE="PHYSICAL">
    <mets:div ID="diglib-1787-phys-0000" TYPE="physSequence">
      <mets:div ID="diglib-1787-phys-bdp0002" ORDER="1" TYPE="page" ORDERLABEL="---">
        <mets:fptr FILEID="diglib-1787-img-bdp0002"/>
      </mets:div>
      <mets:div ID="diglib-1787-phys-bdp0003" ORDER="2" TYPE="page" ORDERLABEL="---">
        <mets:fptr FILEID="diglib-1787-img-bdp0003"/>
      </mets:div>
      <mets:div ID="diglib-1787-phys-bdp0004" ORDER="3" TYPE="page" ORDERLABEL="i">
        <mets:fptr FILEID="diglib-1787-img-bdp0004"/>
      </mets:div>
      <mets:div ID="diglib-1787-phys-bdp0005" ORDER="4" TYPE="page" ORDERLABEL="ii">
        <mets:fptr FILEID="diglib-1787-img-bdp0005"/>
      </mets:div>
      <mets:div ID="diglib-1787-phys-bdp0006" ORDER="5" TYPE="page" ORDERLABEL="iii">
        <mets:fptr FILEID="diglib-1787-img-bdp0006"/>
      </mets:div>
      <mets:div ID="diglib-1787-phys-bdp0007" ORDER="6" TYPE="page" ORDERLABEL="iv">
        <mets:fptr FILEID="diglib-1787-img-bdp0007"/>
      </mets:div>
      <mets:div ID="diglib-1787-phys-bdp0008" ORDER="7" TYPE="page" ORDERLABEL="[5]">
        <mets:fptr FILEID="diglib-1787-img-bdp0008"/>
      </mets:div>
      <mets:div ID="diglib-1787-phys-bdp0009" ORDER="8" TYPE="page" ORDERLABEL="[6]">
        <mets:fptr FILEID="diglib-1787-img-bdp0009"/>
      </mets:div>
      <mets:div ID="diglib-1787-phys-bdp0010" ORDER="9" TYPE="page" ORDERLABEL="7">
        <mets:fptr FILEID="diglib-1787-img-bdp0010"/>
      </mets:div>
      <mets:div ID="diglib-1787-phys-bdp0011" ORDER="10" TYPE="page" ORDERLABEL="8">
        <mets:fptr FILEID="diglib-1787-img-bdp0011"/>
      </mets:div>
      <mets:div ID="diglib-1787-phys-bdp0012" ORDER="11" TYPE="page" ORDERLABEL="9">
        <mets:fptr FILEID="diglib-1787-img-bdp0012"/>
      </mets:div>
      <mets:div ID="diglib-1787-phys-bdp0013" ORDER="12" TYPE="page" ORDERLABEL="10">
        <mets:fptr FILEID="diglib-1787-img-bdp0013"/>
      </mets:div>
      <mets:div ID="diglib-1787-phys-bdp0014" ORDER="13" TYPE="page" ORDERLABEL="11">
        <mets:fptr FILEID="diglib-1787-img-bdp0014"/>
      </mets:div>
      <mets:div ID="diglib-1787-phys-bdp0015" ORDER="14" TYPE="page" ORDERLABEL="12">
        <mets:fptr FILEID="diglib-1787-img-bdp0015"/>
      </mets:div>
      <mets:div ID="diglib-1787-phys-bdp0016" ORDER="15" TYPE="page" ORDERLABEL="13">
        <mets:fptr FILEID="diglib-1787-img-bdp0016"/>
      </mets:div>
      <mets:div ID="diglib-1787-phys-bdp0017" ORDER="16" TYPE="page" ORDERLABEL="14">
        <mets:fptr FILEID="diglib-1787-img-bdp0017"/>
      </mets:div>
      <mets:div ID="diglib-1787-phys-bdp0018" ORDER="17" TYPE="page" ORDERLABEL="15">
        <mets:fptr FILEID="diglib-1787-img-bdp0018"/>
      </mets:div>
      <mets:div ID="diglib-1787-phys-bdp0019" ORDER="18" TYPE="page" ORDERLABEL="16">
        <mets:fptr FILEID="diglib-1787-img-bdp0019"/>
      </mets:div>
      <mets:div ID="diglib-1787-phys-bdp0020" ORDER="19" TYPE="page" ORDERLABEL="17">
        <mets:fptr FILEID="diglib-1787-img-bdp0020"/>
      </mets:div>
      <mets:div ID="diglib-1787-phys-bdp0021" ORDER="20" TYPE="page" ORDERLABEL="18">
        <mets:fptr FILEID="diglib-1787-img-bdp0021"/>
      </mets:div>
      <mets:div ID="diglib-1787-phys-bdp0022" ORDER="21" TYPE="page" ORDERLABEL="19">
        <mets:fptr FILEID="diglib-1787-img-bdp0022"/>
      </mets:div>
      <mets:div ID="diglib-1787-phys-bdp0023" ORDER="22" TYPE="page" ORDERLABEL="20">
        <mets:fptr FILEID="diglib-1787-img-bdp0023"/>
      </mets:div>
      <mets:div ID="diglib-1787-phys-bdp0024" ORDER="23" TYPE="page" ORDERLABEL="21">
        <mets:fptr FILEID="diglib-1787-img-bdp0024"/>
      </mets:div>
      <mets:div ID="diglib-1787-phys-bdp0025" ORDER="24" TYPE="page" ORDERLABEL="22">
        <mets:fptr FILEID="diglib-1787-img-bdp0025"/>
      </mets:div>
      <mets:div ID="diglib-1787-phys-bdp0026" ORDER="25" TYPE="page" ORDERLABEL="23">
        <mets:fptr FILEID="diglib-1787-img-bdp0026"/>
      </mets:div>
      <mets:div ID="diglib-1787-phys-bdp0027" ORDER="26" TYPE="page" ORDERLABEL="24">
        <mets:fptr FILEID="diglib-1787-img-bdp0027"/>
      </mets:div>
      <mets:div ID="diglib-1787-phys-bdp0028" ORDER="27" TYPE="page" ORDERLABEL="[25]">
        <mets:fptr FILEID="diglib-1787-img-bdp0028"/>
      </mets:div>
      <mets:div ID="diglib-1787-phys-bdp0029" ORDER="28" TYPE="page" ORDERLABEL="[26]">
        <mets:fptr FILEID="diglib-1787-img-bdp0029"/>
      </mets:div>
      <mets:div ID="diglib-1787-phys-bdp0030" ORDER="29" TYPE="page" ORDERLABEL="27">
        <mets:fptr FILEID="diglib-1787-img-bdp0030"/>
      </mets:div>
      <mets:div ID="diglib-1787-phys-bdp0031" ORDER="30" TYPE="page" ORDERLABEL="28">
        <mets:fptr FILEID="diglib-1787-img-bdp0031"/>
      </mets:div>
      <mets:div ID="diglib-1787-phys-bdp0032" ORDER="31" TYPE="page" ORDERLABEL="29">
        <mets:fptr FILEID="diglib-1787-img-bdp0032"/>
      </mets:div>
      <mets:div ID="diglib-1787-phys-bdp0033" ORDER="32" TYPE="page" ORDERLABEL="30">
        <mets:fptr FILEID="diglib-1787-img-bdp0033"/>
      </mets:div>
      <mets:div ID="diglib-1787-phys-bdp0034" ORDER="33" TYPE="page" ORDERLABEL="31">
        <mets:fptr FILEID="diglib-1787-img-bdp0034"/>
      </mets:div>
      <mets:div ID="diglib-1787-phys-bdp0035" ORDER="34" TYPE="page" ORDERLABEL="32">
        <mets:fptr FILEID="diglib-1787-img-bdp0035"/>
      </mets:div>
      <mets:div ID="diglib-1787-phys-bdp0036" ORDER="35" TYPE="page" ORDERLABEL="33">
        <mets:fptr FILEID="diglib-1787-img-bdp0036"/>
      </mets:div>
      <mets:div ID="diglib-1787-phys-bdp0037" ORDER="36" TYPE="page" ORDERLABEL="34">
        <mets:fptr FILEID="diglib-1787-img-bdp0037"/>
      </mets:div>
      <mets:div ID="diglib-1787-phys-bdp0038" ORDER="37" TYPE="page" ORDERLABEL="35">
        <mets:fptr FILEID="diglib-1787-img-bdp0038"/>
      </mets:div>
      <mets:div ID="diglib-1787-phys-bdp0039" ORDER="38" TYPE="page" ORDERLABEL="36">
        <mets:fptr FILEID="diglib-1787-img-bdp0039"/>
      </mets:div>
      <mets:div ID="diglib-1787-phys-bdp0040" ORDER="39" TYPE="page" ORDERLABEL="37">
        <mets:fptr FILEID="diglib-1787-img-bdp0040"/>
      </mets:div>
      <mets:div ID="diglib-1787-phys-bdp0041" ORDER="40" TYPE="page" ORDERLABEL="38">
        <mets:fptr FILEID="diglib-1787-img-bdp0041"/>
      </mets:div>
      <mets:div ID="diglib-1787-phys-bdp0042" ORDER="41" TYPE="page" ORDERLABEL="39">
        <mets:fptr FILEID="diglib-1787-img-bdp0042"/>
      </mets:div>
      <mets:div ID="diglib-1787-phys-bdp0043" ORDER="42" TYPE="page" ORDERLABEL="40">
        <mets:fptr FILEID="diglib-1787-img-bdp0043"/>
      </mets:div>
      <mets:div ID="diglib-1787-phys-bdp0044" ORDER="43" TYPE="page" ORDERLABEL="41">
        <mets:fptr FILEID="diglib-1787-img-bdp0044"/>
      </mets:div>
      <mets:div ID="diglib-1787-phys-bdp0045" ORDER="44" TYPE="page" ORDERLABEL="42">
        <mets:fptr FILEID="diglib-1787-img-bdp0045"/>
      </mets:div>
      <mets:div ID="diglib-1787-phys-bdp0046" ORDER="45" TYPE="page" ORDERLABEL="[43]">
        <mets:fptr FILEID="diglib-1787-img-bdp0046"/>
      </mets:div>
      <mets:div ID="diglib-1787-phys-bdp0047" ORDER="46" TYPE="page" ORDERLABEL="[44]">
        <mets:fptr FILEID="diglib-1787-img-bdp0047"/>
      </mets:div>
      <mets:div ID="diglib-1787-phys-bdp0048" ORDER="47" TYPE="page" ORDERLABEL="45">
        <mets:fptr FILEID="diglib-1787-img-bdp0048"/>
      </mets:div>
      <mets:div ID="diglib-1787-phys-bdp0049" ORDER="48" TYPE="page" ORDERLABEL="46">
        <mets:fptr FILEID="diglib-1787-img-bdp0049"/>
      </mets:div>
      <mets:div ID="diglib-1787-phys-bdp0050" ORDER="49" TYPE="page" ORDERLABEL="47">
        <mets:fptr FILEID="diglib-1787-img-bdp0050"/>
      </mets:div>
      <mets:div ID="diglib-1787-phys-bdp0051" ORDER="50" TYPE="page" ORDERLABEL="48">
        <mets:fptr FILEID="diglib-1787-img-bdp0051"/>
      </mets:div>
      <mets:div ID="diglib-1787-phys-bdp0052" ORDER="51" TYPE="page" ORDERLABEL="49">
        <mets:fptr FILEID="diglib-1787-img-bdp0052"/>
      </mets:div>
      <mets:div ID="diglib-1787-phys-bdp0053" ORDER="52" TYPE="page" ORDERLABEL="50">
        <mets:fptr FILEID="diglib-1787-img-bdp0053"/>
      </mets:div>
      <mets:div ID="diglib-1787-phys-bdp0054" ORDER="53" TYPE="page" ORDERLABEL="51">
        <mets:fptr FILEID="diglib-1787-img-bdp0054"/>
      </mets:div>
      <mets:div ID="diglib-1787-phys-bdp0055" ORDER="54" TYPE="page" ORDERLABEL="[52]">
        <mets:fptr FILEID="diglib-1787-img-bdp0055"/>
      </mets:div>
    </mets:div>
  </mets:structMap>

  <mets:structLink>
    <mets:smLink xlink:from="diglib-1787-log-0000" xlink:to="diglib-1787-phys-0000"/>
    <mets:smLink xlink:from="diglib-1787-log-0001" xlink:to="diglib-1787-phys-0001"/>
    <mets:smLink xlink:from="diglib-1787-log-0002" xlink:to="diglib-1787-phys-0003"/>
    <mets:smLink xlink:from="diglib-1787-log-0003" xlink:to="diglib-1787-phys-0007"/>
    <mets:smLink xlink:from="diglib-1787-log-0004" xlink:to="diglib-1787-phys-0027"/>
    <mets:smLink xlink:from="diglib-1787-log-0005" xlink:to="diglib-1787-phys-0045"/>
  </mets:structLink>

</mets:mets>